deboundcer/db_fsm.v
module db_fsm(
    input wire clk, 
    input wire reset,
    input wire sw,
    output reg db
);
//symbolic state declaration
localparam [2:0]
            zero = 3'b000,
            wait1_1 = 3'b001,
            wait1_2 = 3'b010,
            wait1_3 = 3'b011,
            one = 3'b100,
            wait0_1 = 3'b101,
            wait0_2 = 3'b110,
            wait0_3 = 3'b111;

//number of counter bits(2^N*20ns = 10ms tick)
localparam N=19;

//signal declaration
reg[N-1:0] q_reg;
wire [N-1:0] q_next;
wire m_tick;
reg [2:0] state_reg, state_next;

//body
//counter to generate 10ms tick

always @(posedge clk)
    begin
    q_reg <= q_next;
    end
//next-state logic
assign q_next = q_reg+1;
//output tick
assign m_tick = (q_reg == 0) ? 1'b1 : 1'b0;

//debouncing FSM
//state register
always @(posedge clk, posedge(reset))
    if(reset)
        state_reg <= zero;
    else
        state_reg <= state_next;

//next-state logic and output logic
always @*
begin
    state_next = state_reg; //default state : the same
    db = 1'b0;              //default output:0
    case(state_reg)
        zero:
            if(sw)
                state_next = wait1_1;
        wait1_1:
            if(~sw)
                state_next = zero;
            else
                if(m_tick)
                    state_next = wait1_2;
        wait1_2:
            if(~sw)
                state_next = zero;
            else
                if (m_tick)
                    state_next = wait1_3;
        wait1_3:
            if (~sw)
                state_next = zero;
            else
                if(m_tick)
                    state_next = one;
        one:
            begin
                db = 1'b1;
                if(~sw)
                    state_next = wait0_1;
            end
        wait0_1:
            begin
                db = 1'b1;
                if(sw)
                    state_next = one;
                else
                    if(m_tick)
                        state_next = wait0_2;
            end
        wait0_2:
            begin
                db = 1'b1;
                if (sw)
                    state_next = one;
                else
                    if (m_tick)
                        state_next = wait0_3;
            end
        wait0_3:
            begin
                db = 1'b1;
                if(sw)
                    state_next = one;
                else
                    if(m_tick)
                        state_next = zero;
            end
        default: state_next = zero;
    endcase
end
endmodule

deboundcer/debouncer_tb.v
//-------------------------------------------------------------------
//-- Testbench
//-- DEBOUNCER DE 1 BIT
//-------------------------------------------------------------------

`default_nettype none
`define DUMPSTR(x) `"x.vcd`"
`timescale 100 ns / 10 ns
// timescale <time_unit> / <time_precision>

module db_fsm_tb();

    //-- Simulation time: 1us (10 * 100ns)
    parameter DURATION = 300;

    //-- Clock signal. It is not used in this simulation
    reg clk = 0;
    always #0.5 clk = ~clk;

    // a ports
    reg test_reset;
    reg test_sw;
    wire test_db;

    //-- Instantiate the unit to test
    db_fsm UUT(
             .clk(clk),
             .reset(test_reset),
             .sw(test_sw),
             .db(test_db)
           );

    initial begin

        //-- File were to store the simulation results
        $dumpfile(`DUMPSTR(`VCD_OUTPUT));
        $dumpvars(0, db_fsm_tb);

        test_reset = 1;

        #1
        test_reset = 0;

        #1
        test_sw = 1;

        #20
        test_sw = 0;


        #20
        test_sw = 1;
        
        #20
        test_sw = 0;

        #(DURATION) $display("End of simulation");
        $finish;
    end

endmodule

deboundcer/debouncer_tb.vcd
$date
	Wed Jun 21 16:14:38 2023
$end
$version
	Icarus Verilog
$end
$timescale
	1ps
$end
$scope module db_fsm_tb $end
$var wire 1 ! test_db $end
$var reg 1 " clk $end
$var reg 1 # test_reset $end
$var reg 1 $ test_sw $end
$scope module UUT $end
$var wire 1 " clk $end
$var wire 1 # reset $end
$var wire 1 $ sw $end
$var wire 19 % q_next [18:0] $end
$var wire 1 & m_tick $end
$var reg 1 ! db $end
$var reg 19 ' q_reg [18:0] $end
$var reg 3 ( state_next [2:0] $end
$var reg 3 ) state_reg [2:0] $end
$upscope $end
$upscope $end
$enddefinitions $end
#0
$dumpvars
b0 )
b0 (
bx '
x&
bx %
x$
1#
0"
0!
$end
#50000
1"
#100000
0"
0#
#150000
1"
#200000
b1 (
0"
1$
#250000
b1 )
1"
#300000
0"
#350000
1"
#400000
0"
#450000
1"
#500000
0"
#550000
1"
#600000
0"
#650000
1"
#700000
0"
#750000
1"
#800000
0"
#850000
1"
#900000
0"
#950000
1"
#1000000
0"
#1050000
1"
#1100000
0"
#1150000
1"
#1200000
0"
#1250000
1"
#1300000
0"
#1350000
1"
#1400000
0"
#1450000
1"
#1500000
0"
#1550000
1"
#1600000
0"
#1650000
1"
#1700000
0"
#1750000
1"
#1800000
0"
#1850000
1"
#1900000
0"
#1950000
1"
#2000000
0"
#2050000
1"
#2100000
0"
#2150000
1"
#2200000
b0 (
0"
0$
#2250000
b0 )
1"
#2300000
0"
#2350000
1"
#2400000
0"
#2450000
1"
#2500000
0"
#2550000
1"
#2600000
0"
#2650000
1"
#2700000
0"
#2750000
1"
#2800000
0"
#2850000
1"
#2900000
0"
#2950000
1"
#3000000
0"
#3050000
1"
#3100000
0"
#3150000
1"
#3200000
0"
#3250000
1"
#3300000
0"
#3350000
1"
#3400000
0"
#3450000
1"
#3500000
0"
#3550000
1"
#3600000
0"
#3650000
1"
#3700000
0"
#3750000
1"
#3800000
0"
#3850000
1"
#3900000
0"
#3950000
1"
#4000000
0"
#4050000
1"
#4100000
0"
#4150000
1"
#4200000
b1 (
0"
1$
#4250000
b1 )
1"
#4300000
0"
#4350000
1"
#4400000
0"
#4450000
1"
#4500000
0"
#4550000
1"
#4600000
0"
#4650000
1"
#4700000
0"
#4750000
1"
#4800000
0"
#4850000
1"
#4900000
0"
#4950000
1"
#5000000
0"
#5050000
1"
#5100000
0"
#5150000
1"
#5200000
0"
#5250000
1"
#5300000
0"
#5350000
1"
#5400000
0"
#5450000
1"
#5500000
0"
#5550000
1"
#5600000
0"
#5650000
1"
#5700000
0"
#5750000
1"
#5800000
0"
#5850000
1"
#5900000
0"
#5950000
1"
#6000000
0"
#6050000
1"
#6100000
0"
#6150000
1"
#6200000
b0 (
0"
0$
#6250000
b0 )
1"
