edge/edge_detect_gate.v
module edge_detect_gate(
    input wire clk, reset,
    input wire level,
    output wire tick
);
// signal declaration
reg delay_reg ;
// delay register
always @(posedge clk, posedge reset)
    if (reset)
        delay_reg <= 1'b0;
    else
        delay_reg <= level;
// decoding logic
assign tick = ~delay_reg & level;

endmodule

deboundcer/db_fsm.v
module db_fsm (
    input wire clk,
    input wire reset,
    input wire sw,
    output reg db
);
    // Symbolic state declaration
    localparam [2:0]
        zero = 3'b000,
        wait1_1 = 3'b001,
        wait1_2 = 3'b010,
        wait1_3 = 3'b011,
        one = 3'b100,
        wait0_1 = 3'b101,
        wait0_2 = 3'b110,
        wait0_3 = 3'b111;

    // Number of counter bits (2^N * 2^Ons = 10ms tick)
    localparam N = 19;

    // Signal declaration
    reg [N-1:0] q_reg;
    wire [N-1:0] q_next;
    wire m_tick;
    reg [2:0] state_reg, state_next;

    // Counter to generate 10ms tick
    always @(posedge clk or posedge reset)
        if (reset)
            q_reg <= 0;
        else
            q_reg <= q_next;

    // Next state logic
    assign q_next = q_reg + 1;

    // Output tick
    assign m_tick = (q_reg == 0) ? 1'b1 : 1'b0;

    // Debouncing FSM
    always @(posedge clk or posedge reset)
        if (reset)
            state_reg <= zero;
        else
            state_reg <= state_next;

    always @*
    begin
        state_next = state_reg; // Default state: the same
        db = 1'b0;
        case (state_reg)
            zero:
                if (sw)
                    state_next = wait1_1;
            wait1_1:
                if (~sw)
                    state_next = zero;
                else if (m_tick)
                    state_next = wait1_2;
            wait1_2:
                if (~sw)
                    state_next = zero;
                else if (m_tick)
                    state_next = wait1_3;
            wait1_3:
                if (~sw)
                    state_next = zero;
                else if (m_tick)
                    state_next = one;
            one:
                begin
                    db = 1'b1;
                    if (~sw)
                        state_next = wait0_1;
                end
            wait0_1:
                begin
                    if (sw)
                        state_next = one;
                    else if (m_tick)
                        state_next = wait0_2;
                end
            wait0_2:
                begin
                    if (sw)
                        state_next = one;
                    else if (m_tick)
                        state_next = wait0_3;
                end
            wait0_3:
                begin
                    if (sw)
                        state_next = one;
                    else if (m_tick)
                        state_next = zero;
                end
            default:
                state_next = zero;
        endcase
    end
endmodule

inversor/inv.v
module inv(
    input wire [3:0] in,
    output wire [3:0] out
);

assign out = ~in;

endmodule

Main.v
`include "inversor/inv.v"
`include "contador_ud/contador_ud_p.v"
`include "deboundcer/db_fsm.v"
`include "edge/edge_detect_gate.v"
module main2_0(
    input wire clk,
    input wire reset,
    input wire [3:0] BTN,
    output wire [3:0] LEDS
);
//declaro las variables
wire[3:0] BTN_inversados, boton_db, boton_tick;

inv inversador(
    .in(BTN),
    .out(BTN_inversados)
);

//debaunceo los botones
db_fsm boton1(
    .clk(clk),
    .reset(1'b0),
    .sw(BTN[0]),
    .db(boton_db[0])
);
db_fsm boton2(
    .clk(clk),
    .reset(reset),
    .sw(BTN[1]),
    .db(boton_db[1])
);
db_fsm boton3(
    .clk(clk),
    .reset(reset),
    .sw(BTN[2]),
    .db(boton_db[2])
);
db_fsm boton4(
    .clk(clk),
    .reset(reset),
    .sw(BTN[3]),
    .db(boton_db[3])
);

edge_detect_gate eboton1(
    .clk(clk),
    .reset(reset),
    .level(boton_db[0]),
    .tick(boton_tick[0])
);

edge_detect_gate eboton2(
    .clk(clk),
    .reset(reset),
    .level(boton_db[1]),
    .tick(boton_tick[1])
);
edge_detect_gate eboton3(
    .clk(clk),
    .reset(reset),
    .level(boton_db[2]),
    .tick(boton_tick[2])
);
edge_detect_gate eboton4(
    .clk(clk),
    .reset(reset),
    .level(boton_db[3]),
    .tick(boton_tick[3])
);
reg [3:0] c;
always @*
    c <= boton_tick;
assign LEDS = c;

endmodule

Main_tb.v
`default_nettype none
`define DUMPSTR(x) `"x.vcd`"
`timescale 100 ns / 10 ns
module main_tb;
parameter DURATION = 100;


reg clk = 0;
always #0.5 clk = ~clk;
reg reset;
reg [3:0] BOTONES;
wire [3:0] LEDS;

main2_0 UUT (
    .clk(clk),
    .reset(reset),
    .BTN(BOTONES),
    .LEDS(LEDS)
);



initial begin
  $dumpfile(`DUMPSTR(`VCD_OUTPUT));
  $dumpvars(0, main_tb);
    reset= 1;
    #1
    BOTONES[0] = 0;
    BOTONES[1] = 0;
    BOTONES[2] = 0;
    BOTONES[3] = 0;
    reset = 0;
    #15
    BOTONES[0] = 1;

    #15
    BOTONES[0] = 0;

    #12
    BOTONES[0] = 1;

    #11
    BOTONES[0] = 0;
    #15
    BOTONES[0] = 1;

    #15
    BOTONES[0] = 0;
    
    #15
    BOTONES[0] = 1;

    #15
    BOTONES[0] = 0;
    //Numerador
   
   #(DURATION) $display("End of simulation");
  $finish;
end

endmodule

Main_tb.vcd
$date
	Wed Jun 14 11:29:58 2023
$end
$version
	Icarus Verilog
$end
$timescale
	1ps
$end
$scope module main_tb $end
$var wire 4 ! LEDS [3:0] $end
$var reg 4 " BOTONES [3:0] $end
$var reg 1 # clk $end
$var reg 1 $ reset $end
$scope module UUT $end
$var wire 4 % BTN [3:0] $end
$var wire 4 & LEDS [3:0] $end
$var wire 1 # clk $end
$var wire 1 $ reset $end
$var wire 4 ' boton_tick [3:0] $end
$var wire 4 ( boton_db [3:0] $end
$var wire 4 ) BTN_inversados [3:0] $end
$var reg 4 * c [3:0] $end
$scope module boton1 $end
$var wire 1 # clk $end
$var wire 1 + reset $end
$var wire 1 , sw $end
$var wire 19 - q_next [18:0] $end
$var wire 1 . m_tick $end
$var reg 1 / db $end
$var reg 19 0 q_reg [18:0] $end
$var reg 3 1 state_next [2:0] $end
$var reg 3 2 state_reg [2:0] $end
$upscope $end
$scope module boton2 $end
$var wire 1 # clk $end
$var wire 1 $ reset $end
$var wire 1 3 sw $end
$var wire 19 4 q_next [18:0] $end
$var wire 1 5 m_tick $end
$var reg 1 6 db $end
$var reg 19 7 q_reg [18:0] $end
$var reg 3 8 state_next [2:0] $end
$var reg 3 9 state_reg [2:0] $end
$upscope $end
$scope module boton3 $end
$var wire 1 # clk $end
$var wire 1 $ reset $end
$var wire 1 : sw $end
$var wire 19 ; q_next [18:0] $end
$var wire 1 < m_tick $end
$var reg 1 = db $end
$var reg 19 > q_reg [18:0] $end
$var reg 3 ? state_next [2:0] $end
$var reg 3 @ state_reg [2:0] $end
$upscope $end
$scope module boton4 $end
$var wire 1 # clk $end
$var wire 1 $ reset $end
$var wire 1 A sw $end
$var wire 19 B q_next [18:0] $end
$var wire 1 C m_tick $end
$var reg 1 D db $end
$var reg 19 E q_reg [18:0] $end
$var reg 3 F state_next [2:0] $end
$var reg 3 G state_reg [2:0] $end
$upscope $end
$scope module eboton1 $end
$var wire 1 # clk $end
$var wire 1 H level $end
$var wire 1 $ reset $end
$var wire 1 I tick $end
$var reg 1 J delay_reg $end
$upscope $end
$scope module eboton2 $end
$var wire 1 # clk $end
$var wire 1 K level $end
$var wire 1 $ reset $end
$var wire 1 L tick $end
$var reg 1 M delay_reg $end
$upscope $end
$scope module eboton3 $end
$var wire 1 # clk $end
$var wire 1 N level $end
$var wire 1 $ reset $end
$var wire 1 O tick $end
$var reg 1 P delay_reg $end
$upscope $end
$scope module eboton4 $end
$var wire 1 # clk $end
$var wire 1 Q level $end
$var wire 1 $ reset $end
$var wire 1 R tick $end
$var reg 1 S delay_reg $end
$upscope $end
$scope module inversador $end
$var wire 4 T in [3:0] $end
$var wire 4 U out [3:0] $end
$upscope $end
$upscope $end
$upscope $end
$enddefinitions $end
#0
$dumpvars
bx U
bx T
0S
0R
0Q
0P
0O
0N
0M
0L
0K
0J
0I
0H
b0 G
b0 F
b0 E
0D
1C
b1 B
xA
b0 @
b0 ?
b0 >
0=
1<
b1 ;
x:
b0 9
b0 8
b0 7
06
15
b1 4
x3
bx 2
b0 1
bx 0
0/
x.
bx -
x,
0+
b0 *
bx )
b0 (
b0 '
b0 &
bx %
1$
0#
bx "
b0 !
$end
#50000
b0 2
1#
#100000
0A
0:
03
0,
b1111 )
b1111 U
0#
0$
b0 "
b0 %
b0 T
#150000
05
0<
0C
b10 4
b1 7
b10 ;
b1 >
b10 B
b1 E
1#
#200000
0#
#250000
b11 B
b10 E
b11 ;
b10 >
b11 4
b10 7
1#
#300000
0#
#350000
b100 4
b11 7
b100 ;
b11 >
b100 B
b11 E
1#
#400000
0#
#450000
b101 B
b100 E
b101 ;
b100 >
b101 4
b100 7
1#
#500000
0#
#550000
b110 4
b101 7
b110 ;
b101 >
b110 B
b101 E
1#
#600000
0#
#650000
b111 B
b110 E
b111 ;
b110 >
b111 4
b110 7
1#
#700000
0#
#750000
b1000 4
b111 7
b1000 ;
b111 >
b1000 B
b111 E
1#
#800000
0#
#850000
b1001 B
b1000 E
b1001 ;
b1000 >
b1001 4
b1000 7
1#
#900000
0#
#950000
b1010 4
b1001 7
b1010 ;
b1001 >
b1010 B
b1001 E
1#
#1000000
0#
#1050000
b1011 B
b1010 E
b1011 ;
b1010 >
b1011 4
b1010 7
1#
#1100000
0#
#1150000
b1100 4
b1011 7
b1100 ;
b1011 >
b1100 B
b1011 E
1#
#1200000
0#
#1250000
b1101 B
b1100 E
b1101 ;
b1100 >
b1101 4
b1100 7
1#
#1300000
0#
#1350000
b1110 4
b1101 7
b1110 ;
b1101 >
b1110 B
b1101 E
1#
#1400000
0#
#1450000
b1111 B
b1110 E
b1111 ;
b1110 >
b1111 4
b1110 7
1#
#1500000
0#
#1550000
b10000 4
b1111 7
b10000 ;
b1111 >
b10000 B
b1111 E
1#
#1600000
b1 1
1,
b1110 )
b1110 U
0#
b1 "
b1 %
b1 T
#1650000
b1 2
b10001 B
b10000 E
b10001 ;
b10000 >
b10001 4
b10000 7
1#
#1700000
0#
#1750000
b10010 4
b10001 7
b10010 ;
b10001 >
b10010 B
b10001 E
1#
#1800000
0#
#1850000
b10011 B
b10010 E
b10011 ;
b10010 >
b10011 4
b10010 7
1#
#1900000
0#
#1950000
b10100 4
b10011 7
b10100 ;
b10011 >
b10100 B
b10011 E
1#
#2000000
0#
#2050000
b10101 B
b10100 E
b10101 ;
b10100 >
b10101 4
b10100 7
1#
#2100000
0#
#2150000
b10110 4
b10101 7
b10110 ;
b10101 >
b10110 B
b10101 E
1#
#2200000
0#
#2250000
b10111 B
b10110 E
b10111 ;
b10110 >
b10111 4
b10110 7
1#
#2300000
0#
#2350000
b11000 4
b10111 7
b11000 ;
b10111 >
b11000 B
b10111 E
1#
#2400000
0#
#2450000
b11001 B
b11000 E
b11001 ;
b11000 >
b11001 4
b11000 7
1#
#2500000
0#
#2550000
b11010 4
b11001 7
b11010 ;
b11001 >
b11010 B
b11001 E
1#
#2600000
0#
#2650000
b11011 B
b11010 E
b11011 ;
b11010 >
b11011 4
b11010 7
1#
#2700000
0#
#2750000
b11100 4
b11011 7
b11100 ;
b11011 >
b11100 B
b11011 E
1#
#2800000
0#
#2850000
b11101 B
b11100 E
b11101 ;
b11100 >
b11101 4
b11100 7
1#
#2900000
0#
#2950000
b11110 4
b11101 7
b11110 ;
b11101 >
b11110 B
b11101 E
1#
#3000000
0#
#3050000
b11111 B
b11110 E
b11111 ;
b11110 >
b11111 4
b11110 7
1#
#3100000
b0 1
0,
b1111 )
b1111 U
0#
b0 "
b0 %
b0 T
#3150000
b0 2
b100000 4
b11111 7
b100000 ;
b11111 >
b100000 B
b11111 E
1#
#3200000
0#
#3250000
b100001 B
b100000 E
b100001 ;
b100000 >
b100001 4
b100000 7
1#
#3300000
0#
#3350000
b100010 4
b100001 7
b100010 ;
b100001 >
b100010 B
b100001 E
1#
#3400000
0#
#3450000
b100011 B
b100010 E
b100011 ;
b100010 >
b100011 4
b100010 7
1#
#3500000
0#
#3550000
b100100 4
b100011 7
b100100 ;
b100011 >
b100100 B
b100011 E
1#
#3600000
0#
#3650000
b100101 B
b100100 E
b100101 ;
b100100 >
b100101 4
b100100 7
1#
#3700000
0#
#3750000
b100110 4
b100101 7
b100110 ;
b100101 >
b100110 B
b100101 E
1#
#3800000
0#
#3850000
b100111 B
b100110 E
b100111 ;
b100110 >
b100111 4
b100110 7
1#
#3900000
0#
#3950000
b101000 4
b100111 7
b101000 ;
b100111 >
b101000 B
b100111 E
1#
#4000000
0#
#4050000
b101001 B
b101000 E
b101001 ;
b101000 >
b101001 4
b101000 7
1#
#4100000
0#
#4150000
b101010 4
b101001 7
b101010 ;
b101001 >
b101010 B
b101001 E
1#
#4200000
0#
#4250000
b101011 B
b101010 E
b101011 ;
b101010 >
b101011 4
b101010 7
1#
#4300000
b1 1
1,
b1110 )
b1110 U
0#
b1 "
b1 %
b1 T
#4350000
b1 2
b101100 4
b101011 7
b101100 ;
b101011 >
b101100 B
b101011 E
1#
#4400000
0#
#4450000
b101101 B
b101100 E
b101101 ;
b101100 >
b101101 4
b101100 7
1#
#4500000
0#
#4550000
b101110 4
b101101 7
b101110 ;
b101101 >
b101110 B
b101101 E
1#
#4600000
0#
#4650000
b101111 B
b101110 E
b101111 ;
b101110 >
b101111 4
b101110 7
1#
#4700000
0#
#4750000
b110000 4
b101111 7
b110000 ;
b101111 >
b110000 B
b101111 E
1#
#4800000
0#
#4850000
b110001 B
b110000 E
b110001 ;
b110000 >
b110001 4
b110000 7
1#
#4900000
0#
#4950000
b110010 4
b110001 7
b110010 ;
b110001 >
b110010 B
b110001 E
1#
#5000000
0#
#5050000
b110011 B
b110010 E
b110011 ;
b110010 >
b110011 4
b110010 7
1#
#5100000
0#
#5150000
b110100 4
b110011 7
b110100 ;
b110011 >
b110100 B
b110011 E
1#
#5200000
0#
#5250000
b110101 B
b110100 E
b110101 ;
b110100 >
b110101 4
b110100 7
1#
#5300000
0#
#5350000
b110110 4
b110101 7
b110110 ;
b110101 >
b110110 B
b110101 E
1#
#5400000
b0 1
0,
b1111 )
b1111 U
0#
b0 "
b0 %
b0 T
#5450000
b0 2
b110111 B
b110110 E
b110111 ;
b110110 >
b110111 4
b110110 7
1#
#5500000
0#
#5550000
b111000 4
b110111 7
b111000 ;
b110111 >
b111000 B
b110111 E
1#
#5600000
0#
#5650000
b111001 B
b111000 E
b111001 ;
b111000 >
b111001 4
b111000 7
1#
#5700000
0#
#5750000
b111010 4
b111001 7
b111010 ;
b111001 >
b111010 B
b111001 E
1#
#5800000
0#
#5850000
b111011 B
b111010 E
b111011 ;
b111010 >
b111011 4
b111010 7
1#
#5900000
0#
#5950000
b111100 4
b111011 7
b111100 ;
b111011 >
b111100 B
b111011 E
1#
#6000000
0#
#6050000
b111101 B
b111100 E
b111101 ;
b111100 >
b111101 4
b111100 7
1#
#6100000
0#
#6150000
b111110 4
b111101 7
b111110 ;
b111101 >
b111110 B
b111101 E
1#
#6200000
0#
#6250000
b111111 B
b111110 E
b111111 ;
b111110 >
b111111 4
b111110 7
1#
#6300000
0#
#6350000
b1000000 4
b111111 7
b1000000 ;
b111111 >
b1000000 B
b111111 E
1#
#6400000
0#
#6450000
b1000001 B
b1000000 E
b1000001 ;
b1000000 >
b1000001 4
b1000000 7
1#
#6500000
0#
#6550000
b1000010 4
b1000001 7
b1000010 ;
b1000001 >
b1000010 B
b1000001 E
1#
#6600000
0#
#6650000
b1000011 B
b1000010 E
b1000011 ;
b1000010 >
b1000011 4
b1000010 7
1#
#6700000
0#
#6750000
b1000100 4
b1000011 7
b1000100 ;
b1000011 >
b1000100 B
b1000011 E
1#
#6800000
0#
#6850000
b1000101 B
b1000100 E
b1000101 ;
b1000100 >
b1000101 4
b1000100 7
1#
#6900000
b1 1
1,
b1110 )
b1110 U
0#
b1 "
b1 %
b1 T
#6950000
b1 2
b1000110 4
b1000101 7
b1000110 ;
b1000101 >
b1000110 B
b1000101 E
1#
#7000000
0#
#7050000
b1000111 B
b1000110 E
b1000111 ;
b1000110 >
b1000111 4
b1000110 7
1#
#7100000
0#
#7150000
b1001000 4
b1000111 7
b1001000 ;
b1000111 >
b1001000 B
b1000111 E
1#
#7200000
0#
#7250000
b1001001 B
b1001000 E
b1001001 ;
b1001000 >
b1001001 4
b1001000 7
1#
#7300000
0#
#7350000
b1001010 4
b1001001 7
b1001010 ;
b1001001 >
b1001010 B
b1001001 E
1#
#7400000
0#
#7450000
b1001011 B
b1001010 E
b1001011 ;
b1001010 >
b1001011 4
b1001010 7
1#
#7500000
0#
#7550000
b1001100 4
b1001011 7
b1001100 ;
b1001011 >
b1001100 B
b1001011 E
1#
#7600000
0#
#7650000
b1001101 B
b1001100 E
b1001101 ;
b1001100 >
b1001101 4
b1001100 7
1#
#7700000
0#
#7750000
b1001110 4
b1001101 7
b1001110 ;
b1001101 >
b1001110 B
b1001101 E
1#
#7800000
0#
#7850000
b1001111 B
b1001110 E
b1001111 ;
b1001110 >
b1001111 4
b1001110 7
1#
#7900000
0#
#7950000
b1010000 4
b1001111 7
b1010000 ;
b1001111 >
b1010000 B
b1001111 E
1#
#8000000
0#
#8050000
b1010001 B
b1010000 E
b1010001 ;
b1010000 >
b1010001 4
b1010000 7
1#
#8100000
0#
#8150000
b1010010 4
b1010001 7
b1010010 ;
b1010001 >
b1010010 B
b1010001 E
1#
#8200000
0#
#8250000
b1010011 B
b1010010 E
b1010011 ;
b1010010 >
b1010011 4
b1010010 7
1#
#8300000
0#
#8350000
b1010100 4
b1010011 7
b1010100 ;
b1010011 >
b1010100 B
b1010011 E
1#
#8400000
b0 1
0,
b1111 )
b1111 U
0#
b0 "
b0 %
b0 T
#8450000
b0 2
b1010101 B
b1010100 E
b1010101 ;
b1010100 >
b1010101 4
b1010100 7
1#
#8500000
0#
#8550000
b1010110 4
b1010101 7
b1010110 ;
b1010101 >
b1010110 B
b1010101 E
1#
#8600000
0#
#8650000
b1010111 B
b1010110 E
b1010111 ;
b1010110 >
b1010111 4
b1010110 7
1#
#8700000
0#
#8750000
b1011000 4
b1010111 7
b1011000 ;
b1010111 >
b1011000 B
b1010111 E
1#
#8800000
0#
#8850000
b1011001 B
b1011000 E
b1011001 ;
b1011000 >
b1011001 4
b1011000 7
1#
#8900000
0#
#8950000
b1011010 4
b1011001 7
b1011010 ;
b1011001 >
b1011010 B
b1011001 E
1#
#9000000
0#
#9050000
b1011011 B
b1011010 E
b1011011 ;
b1011010 >
b1011011 4
b1011010 7
1#
#9100000
0#
#9150000
b1011100 4
b1011011 7
b1011100 ;
b1011011 >
b1011100 B
b1011011 E
1#
#9200000
0#
#9250000
b1011101 B
b1011100 E
b1011101 ;
b1011100 >
b1011101 4
b1011100 7
1#
#9300000
0#
#9350000
b1011110 4
b1011101 7
b1011110 ;
b1011101 >
b1011110 B
b1011101 E
1#
#9400000
0#
#9450000
b1011111 B
b1011110 E
b1011111 ;
b1011110 >
b1011111 4
b1011110 7
1#
#9500000
0#
#9550000
b1100000 4
b1011111 7
b1100000 ;
b1011111 >
b1100000 B
b1011111 E
1#
#9600000
0#
#9650000
b1100001 B
b1100000 E
b1100001 ;
b1100000 >
b1100001 4
b1100000 7
1#
#9700000
0#
#9750000
b1100010 4
b1100001 7
b1100010 ;
b1100001 >
b1100010 B
b1100001 E
1#
#9800000
0#
#9850000
b1100011 B
b1100010 E
b1100011 ;
b1100010 >
b1100011 4
b1100010 7
1#
#9900000
b1 1
1,
b1110 )
b1110 U
0#
b1 "
b1 %
b1 T
#9950000
b1 2
b1100100 4
b1100011 7
b1100100 ;
b1100011 >
b1100100 B
b1100011 E
1#
#10000000
0#
#10050000
b1100101 B
b1100100 E
b1100101 ;
b1100100 >
b1100101 4
b1100100 7
1#
#10100000
0#
#10150000
b1100110 4
b1100101 7
b1100110 ;
b1100101 >
b1100110 B
b1100101 E
1#
#10200000
0#
#10250000
b1100111 B
b1100110 E
b1100111 ;
b1100110 >
b1100111 4
b1100110 7
1#
#10300000
0#
#10350000
b1101000 4
b1100111 7
b1101000 ;
b1100111 >
b1101000 B
b1100111 E
1#
#10400000
0#
#10450000
b1101001 B
b1101000 E
b1101001 ;
b1101000 >
b1101001 4
b1101000 7
1#
#10500000
0#
#10550000
b1101010 4
b1101001 7
b1101010 ;
b1101001 >
b1101010 B
b1101001 E
1#
#10600000
0#
#10650000
b1101011 B
b1101010 E
b1101011 ;
b1101010 >
b1101011 4
b1101010 7
1#
#10700000
0#
#10750000
b1101100 4
b1101011 7
b1101100 ;
b1101011 >
b1101100 B
b1101011 E
1#
#10800000
0#
#10850000
b1101101 B
b1101100 E
b1101101 ;
b1101100 >
b1101101 4
b1101100 7
1#
#10900000
0#
#10950000
b1101110 4
b1101101 7
b1101110 ;
b1101101 >
b1101110 B
b1101101 E
1#
#11000000
0#
#11050000
b1101111 B
b1101110 E
b1101111 ;
b1101110 >
b1101111 4
b1101110 7
1#
#11100000
0#
#11150000
b1110000 4
b1101111 7
b1110000 ;
b1101111 >
b1110000 B
b1101111 E
1#
#11200000
0#
#11250000
b1110001 B
b1110000 E
b1110001 ;
b1110000 >
b1110001 4
b1110000 7
1#
#11300000
0#
#11350000
b1110010 4
b1110001 7
b1110010 ;
b1110001 >
b1110010 B
b1110001 E
1#
#11400000
b0 1
0,
b1111 )
b1111 U
0#
b0 "
b0 %
b0 T
#11450000
b0 2
b1110011 B
b1110010 E
b1110011 ;
b1110010 >
b1110011 4
b1110010 7
1#
#11500000
0#
#11550000
b1110100 4
b1110011 7
b1110100 ;
b1110011 >
b1110100 B
b1110011 E
1#
#11600000
0#
#11650000
b1110101 B
b1110100 E
b1110101 ;
b1110100 >
b1110101 4
b1110100 7
1#
#11700000
0#
#11750000
b1110110 4
b1110101 7
b1110110 ;
b1110101 >
b1110110 B
b1110101 E
1#
#11800000
0#
#11850000
b1110111 B
b1110110 E
b1110111 ;
b1110110 >
b1110111 4
b1110110 7
1#
#11900000
0#
#11950000
b1111000 4
b1110111 7
b1111000 ;
b1110111 >
b1111000 B
b1110111 E
1#
#12000000
0#
#12050000
b1111001 B
b1111000 E
b1111001 ;
b1111000 >
b1111001 4
b1111000 7
1#
#12100000
0#
#12150000
b1111010 4
b1111001 7
b1111010 ;
b1111001 >
b1111010 B
b1111001 E
1#
#12200000
0#
#12250000
b1111011 B
b1111010 E
b1111011 ;
b1111010 >
b1111011 4
b1111010 7
1#
#12300000
0#
#12350000
b1111100 4
b1111011 7
b1111100 ;
b1111011 >
b1111100 B
b1111011 E
1#
#12400000
0#
#12450000
b1111101 B
b1111100 E
b1111101 ;
b1111100 >
b1111101 4
b1111100 7
1#
#12500000
0#
#12550000
b1111110 4
b1111101 7
b1111110 ;
b1111101 >
b1111110 B
b1111101 E
1#
#12600000
0#
#12650000
b1111111 B
b1111110 E
b1111111 ;
b1111110 >
b1111111 4
b1111110 7
1#
#12700000
0#
#12750000
b10000000 4
b1111111 7
b10000000 ;
b1111111 >
b10000000 B
b1111111 E
1#
#12800000
0#
#12850000
b10000001 B
b10000000 E
b10000001 ;
b10000000 >
b10000001 4
b10000000 7
1#
#12900000
0#
#12950000
b10000010 4
b10000001 7
b10000010 ;
b10000001 >
b10000010 B
b10000001 E
1#
#13000000
0#
#13050000
b10000011 B
b10000010 E
b10000011 ;
b10000010 >
b10000011 4
b10000010 7
1#
#13100000
0#
#13150000
b10000100 4
b10000011 7
b10000100 ;
b10000011 >
b10000100 B
b10000011 E
1#
#13200000
0#
#13250000
b10000101 B
b10000100 E
b10000101 ;
b10000100 >
b10000101 4
b10000100 7
1#
#13300000
0#
#13350000
b10000110 4
b10000101 7
b10000110 ;
b10000101 >
b10000110 B
b10000101 E
1#
#13400000
0#
#13450000
b10000111 B
b10000110 E
b10000111 ;
b10000110 >
b10000111 4
b10000110 7
1#
#13500000
0#
#13550000
b10001000 4
b10000111 7
b10001000 ;
b10000111 >
b10001000 B
b10000111 E
1#
#13600000
0#
#13650000
b10001001 B
b10001000 E
b10001001 ;
b10001000 >
b10001001 4
b10001000 7
1#
#13700000
0#
#13750000
b10001010 4
b10001001 7
b10001010 ;
b10001001 >
b10001010 B
b10001001 E
1#
#13800000
0#
#13850000
b10001011 B
b10001010 E
b10001011 ;
b10001010 >
b10001011 4
b10001010 7
1#
#13900000
0#
#13950000
b10001100 4
b10001011 7
b10001100 ;
b10001011 >
b10001100 B
b10001011 E
1#
#14000000
0#
#14050000
b10001101 B
b10001100 E
b10001101 ;
b10001100 >
b10001101 4
b10001100 7
1#
#14100000
0#
#14150000
b10001110 4
b10001101 7
b10001110 ;
b10001101 >
b10001110 B
b10001101 E
1#
#14200000
0#
#14250000
b10001111 B
b10001110 E
b10001111 ;
b10001110 >
b10001111 4
b10001110 7
1#
#14300000
0#
#14350000
b10010000 4
b10001111 7
b10010000 ;
b10001111 >
b10010000 B
b10001111 E
1#
#14400000
0#
#14450000
b10010001 B
b10010000 E
b10010001 ;
b10010000 >
b10010001 4
b10010000 7
1#
#14500000
0#
#14550000
b10010010 4
b10010001 7
b10010010 ;
b10010001 >
b10010010 B
b10010001 E
1#
#14600000
0#
#14650000
b10010011 B
b10010010 E
b10010011 ;
b10010010 >
b10010011 4
b10010010 7
1#
#14700000
0#
#14750000
b10010100 4
b10010011 7
b10010100 ;
b10010011 >
b10010100 B
b10010011 E
1#
#14800000
0#
#14850000
b10010101 B
b10010100 E
b10010101 ;
b10010100 >
b10010101 4
b10010100 7
1#
#14900000
0#
#14950000
b10010110 4
b10010101 7
b10010110 ;
b10010101 >
b10010110 B
b10010101 E
1#
#15000000
0#
#15050000
b10010111 B
b10010110 E
b10010111 ;
b10010110 >
b10010111 4
b10010110 7
1#
#15100000
0#
#15150000
b10011000 4
b10010111 7
b10011000 ;
b10010111 >
b10011000 B
b10010111 E
1#
#15200000
0#
#15250000
b10011001 B
b10011000 E
b10011001 ;
b10011000 >
b10011001 4
b10011000 7
1#
#15300000
0#
#15350000
b10011010 4
b10011001 7
b10011010 ;
b10011001 >
b10011010 B
b10011001 E
1#
#15400000
0#
#15450000
b10011011 B
b10011010 E
b10011011 ;
b10011010 >
b10011011 4
b10011010 7
1#
#15500000
0#
#15550000
b10011100 4
b10011011 7
b10011100 ;
b10011011 >
b10011100 B
b10011011 E
1#
#15600000
0#
#15650000
b10011101 B
b10011100 E
b10011101 ;
b10011100 >
b10011101 4
b10011100 7
1#
#15700000
0#
#15750000
b10011110 4
b10011101 7
b10011110 ;
b10011101 >
b10011110 B
b10011101 E
1#
#15800000
0#
#15850000
b10011111 B
b10011110 E
b10011111 ;
b10011110 >
b10011111 4
b10011110 7
1#
#15900000
0#
#15950000
b10100000 4
b10011111 7
b10100000 ;
b10011111 >
b10100000 B
b10011111 E
1#
#16000000
0#
#16050000
b10100001 B
b10100000 E
b10100001 ;
b10100000 >
b10100001 4
b10100000 7
1#
#16100000
0#
#16150000
b10100010 4
b10100001 7
b10100010 ;
b10100001 >
b10100010 B
b10100001 E
1#
#16200000
0#
#16250000
b10100011 B
b10100010 E
b10100011 ;
b10100010 >
b10100011 4
b10100010 7
1#
#16300000
0#
#16350000
b10100100 4
b10100011 7
b10100100 ;
b10100011 >
b10100100 B
b10100011 E
1#
#16400000
0#
#16450000
b10100101 B
b10100100 E
b10100101 ;
b10100100 >
b10100101 4
b10100100 7
1#
#16500000
0#
#16550000
b10100110 4
b10100101 7
b10100110 ;
b10100101 >
b10100110 B
b10100101 E
1#
#16600000
0#
#16650000
b10100111 B
b10100110 E
b10100111 ;
b10100110 >
b10100111 4
b10100110 7
1#
#16700000
0#
#16750000
b10101000 4
b10100111 7
b10101000 ;
b10100111 >
b10101000 B
b10100111 E
1#
#16800000
0#
#16850000
b10101001 B
b10101000 E
b10101001 ;
b10101000 >
b10101001 4
b10101000 7
1#
#16900000
0#
#16950000
b10101010 4
b10101001 7
b10101010 ;
b10101001 >
b10101010 B
b10101001 E
1#
#17000000
0#
#17050000
b10101011 B
b10101010 E
b10101011 ;
b10101010 >
b10101011 4
b10101010 7
1#
#17100000
0#
#17150000
b10101100 4
b10101011 7
b10101100 ;
b10101011 >
b10101100 B
b10101011 E
1#
#17200000
0#
#17250000
b10101101 B
b10101100 E
b10101101 ;
b10101100 >
b10101101 4
b10101100 7
1#
#17300000
0#
#17350000
b10101110 4
b10101101 7
b10101110 ;
b10101101 >
b10101110 B
b10101101 E
1#
#17400000
0#
#17450000
b10101111 B
b10101110 E
b10101111 ;
b10101110 >
b10101111 4
b10101110 7
1#
#17500000
0#
#17550000
b10110000 4
b10101111 7
b10110000 ;
b10101111 >
b10110000 B
b10101111 E
1#
#17600000
0#
#17650000
b10110001 B
b10110000 E
b10110001 ;
b10110000 >
b10110001 4
b10110000 7
1#
#17700000
0#
#17750000
b10110010 4
b10110001 7
b10110010 ;
b10110001 >
b10110010 B
b10110001 E
1#
#17800000
0#
#17850000
b10110011 B
b10110010 E
b10110011 ;
b10110010 >
b10110011 4
b10110010 7
1#
#17900000
0#
#17950000
b10110100 4
b10110011 7
b10110100 ;
b10110011 >
b10110100 B
b10110011 E
1#
#18000000
0#
#18050000
b10110101 B
b10110100 E
b10110101 ;
b10110100 >
b10110101 4
b10110100 7
1#
#18100000
0#
#18150000
b10110110 4
b10110101 7
b10110110 ;
b10110101 >
b10110110 B
b10110101 E
1#
#18200000
0#
#18250000
b10110111 B
b10110110 E
b10110111 ;
b10110110 >
b10110111 4
b10110110 7
1#
#18300000
0#
#18350000
b10111000 4
b10110111 7
b10111000 ;
b10110111 >
b10111000 B
b10110111 E
1#
#18400000
0#
#18450000
b10111001 B
b10111000 E
b10111001 ;
b10111000 >
b10111001 4
b10111000 7
1#
#18500000
0#
#18550000
b10111010 4
b10111001 7
b10111010 ;
b10111001 >
b10111010 B
b10111001 E
1#
#18600000
0#
#18650000
b10111011 B
b10111010 E
b10111011 ;
b10111010 >
b10111011 4
b10111010 7
1#
#18700000
0#
#18750000
b10111100 4
b10111011 7
b10111100 ;
b10111011 >
b10111100 B
b10111011 E
1#
#18800000
0#
#18850000
b10111101 B
b10111100 E
b10111101 ;
b10111100 >
b10111101 4
b10111100 7
1#
