edge/edge_detect_gate.v
module edge_detect_gate(
    input wire clk, reset,
    input wire level,
    output wire tick
);
// signal declaration
reg delay_reg ;
// delay register
always @(posedge clk, posedge reset)
    if (reset)
        delay_reg <= 1'b0;
    else
        delay_reg <= level;
// decoding logic
assign tick = ~delay_reg & level;

endmodule

deboundcer/db_fsm.v
module db_fsm(
    input wire clk, reset,
    input wire sw,
    output reg db
);
//symbolic state declaration
localparam [2:0]
            zero = 3'b000,
            wait1_1 = 3'b001,
            wait1_2 = 3'b010,
            wait1_3 = 3'b011,
            one = 3'b100,
            wait0_1 = 3'b101,
            wait0_2 = 3'b110,
            wait0_3 = 3'b111;

//number of counter bits(2^N*20ns = 10ms tick)
localparam N=19;

//signal declaration
reg[N-1:0] q_reg;
wire [N-1:0] q_next;
wire m_tick;
reg [2:0] state_reg, state_next;

//body
//counter to generate 10ms tick

always @(posedge clk)
    q_reg <= q_next;
    //next-state logic
assign q_next = q_reg+1;
//output tick
assign m_tick = (q_reg == 0) ? 1'b1 : 1'b0;

//debouncing FSM
//state register
always @(posedge clk, posedge(reset))
    if(reset)
        state_reg <= zero;
    else
        state_reg <= state_next;

//next-state logic and output logic
always @*
begin
    state_next = state_reg; //default state : the same
    db = 1'b0;              //default output:0
    case(state_reg)
        zero:
            if(sw)
                state_next = wait1_1;
        wait1_1:
            if(~sw)
                state_next = zero;
            else
                if(m_tick)
                    state_next = wait1_2;
        wait1_2:
            if(~sw)
                state_next = zero;
            else
                if (m_tick)
                    state_next = wait1_3;
        wait1_3:
            if (~sw)
                state_next = zero;
            else
                if(m_tick)
                    state_next = one;
        one:
            begin
                db = 1'b1;
                if(~sw)
                    state_next = wait0_1;
            end
        wait0_1
            begin
                db = 1'b1;
                if(sw)
                    state_next = one;
                else
                    if(m_tick)
                        state_next = wait0_2;
            end
        wait0_2
            begin
                db = 1'b1;
                if (sw)
                    state_next = one;
                else
                    if (m_tick)
                        state_next = wait0_3;
            end
        wait0_3
            begin
                db = 1'b1;
                if(sw)
                    state_next = one;
                else
                    if(m_tick)
                        state_next = zero;
            end
        default: state_next = zero;
    endcase
end
endmodule

inversor/inv.v
module inv(
    input wire [3:0] in,
    output wire [3:0] out
);

assign out = ~in;

endmodule

Main.v
`include "inversor/inv.v"
`include "contador_ud/contador_ud_p.v"
`include "deboundcer/db_fsm.v"
`include "edge/edge_detect_gate.v"

module main2_0(
    input wire clk,
    input wire reset,
    input wire [3:0] BTN,
    output wire [3:0] LEDS
);
//declaro las variables
wire[3:0] BTN_inversados, boton_db, boton_tick;
reg[3:0] c = 4'b0000;
localparam 
    cero = 1'b0;

//Invierto la senial de los botones
inv inversador(
    .in(BTN),
    .out(BTN_inversados)
);

db_fsm boton1(
    .clk(clk),
    .reset(cero),
    .sw(BTN_inversados[0]),
    .db(boton_db[0])
);
db_fsm boton2(
    .clk(clk),
    .reset(cero),
    .sw(BTN_inversados[1]),
    .db(boton_db[1])
);
db_fsm boton3(
    .clk(clk),
    .reset(cero),
    .sw(BTN_inversados[2]),
    .db(boton_db[2])
);
db_fsm boton4(
    .clk(clk),
    .reset(cero),
    .sw(BTN_inversados[3]),
    .db(boton_db[3])
);

edge_detect_gate eboton1(
    .clk(clk),
    .reset(cero),
    .level(boton_db[0]),
    .tick(boton_tick[0])
);

edge_detect_gate eboton2(
    .clk(clk),
    .reset(cero),
    .level(boton_db[1]),
    .tick(boton_tick[1])
);
edge_detect_gate eboton3(
    .clk(clk),
    .reset(cero),
    .level(boton_db[2]),
    .tick(boton_tick[2])
);
edge_detect_gate eboton4(
    .clk(clk),
    .reset(cero),
    .level(boton_db[3]),
    .tick(boton_tick[3])
);
always @* begin
    if(boton_tick[0]) begin
        c[0] = 1;
    end 
    else begin
        if(boton_tick[1]) begin
        c[0] = 0;
        end
    end
end
assign LEDS[0] = c[0];
assign LEDS[1] = c[1];
assign LEDS[2] = c[2];
assign LEDS[3] = c[3];

endmodule

Main_tb.v
`default_nettype none
`define DUMPSTR(x) `"x.vcd`"
`timescale 100 ns / 10 ns
module main_tb();
  parameter DURATION = 300;


  reg clk = 0;
  always #0.5 clk = ~clk;
  reg reset;
  reg [3:0] BOTONES;
  wire [3:0] LEDS;

  main2_0 UUT (
      .clk(clk),
      .reset(reset),
      .BTN(BOTONES),
      .LEDS(LEDS)
  );



  initial begin
    $dumpfile(`DUMPSTR(`VCD_OUTPUT));
    $dumpvars(0, main_tb);
      reset= 1;
      #1
      BOTONES[0] = 0;
      BOTONES[1] = 0;
      BOTONES[2] = 0;
      BOTONES[3] = 0;
      reset = 0;
      #10
      BOTONES[0] = 1;

      #10
      BOTONES[0] = 0;

      #15
      BOTONES[0] = 1;

      #10
      BOTONES[0] = 0;
      #15
      BOTONES[0] = 1;

      #10
      BOTONES[0] = 0;
      
      #10
      BOTONES[0] = 1;

      //Numerador
    
    #(DURATION) $display("End of simulation");
    $finish;
  end
endmodule

Main_tb.vcd
$date
	Wed Jun 21 15:44:59 2023
$end
$version
	Icarus Verilog
$end
$timescale
	1ps
$end
$scope module main_tb $end
$var wire 4 ! LEDS [3:0] $end
$var reg 4 " BOTONES [3:0] $end
$var reg 1 # clk $end
$var reg 1 $ reset $end
$scope module UUT $end
$var wire 4 % BTN [3:0] $end
$var wire 1 # clk $end
$var wire 1 $ reset $end
$var wire 4 & boton_tick [3:0] $end
$var wire 4 ' boton_db [3:0] $end
$var wire 4 ( LEDS [3:0] $end
$var wire 4 ) BTN_inversados [3:0] $end
$var reg 4 * c [3:0] $end
$scope module boton1 $end
$var wire 1 # clk $end
$var wire 1 + reset $end
$var wire 1 , sw $end
$var wire 19 - q_next [18:0] $end
$var wire 1 . m_tick $end
$var reg 1 / db $end
$var reg 19 0 q_reg [18:0] $end
$var reg 3 1 state_next [2:0] $end
$var reg 3 2 state_reg [2:0] $end
$upscope $end
$scope module boton2 $end
$var wire 1 # clk $end
$var wire 1 3 reset $end
$var wire 1 4 sw $end
$var wire 19 5 q_next [18:0] $end
$var wire 1 6 m_tick $end
$var reg 1 7 db $end
$var reg 19 8 q_reg [18:0] $end
$var reg 3 9 state_next [2:0] $end
$var reg 3 : state_reg [2:0] $end
$upscope $end
$scope module boton3 $end
$var wire 1 # clk $end
$var wire 1 ; reset $end
$var wire 1 < sw $end
$var wire 19 = q_next [18:0] $end
$var wire 1 > m_tick $end
$var reg 1 ? db $end
$var reg 19 @ q_reg [18:0] $end
$var reg 3 A state_next [2:0] $end
$var reg 3 B state_reg [2:0] $end
$upscope $end
$scope module boton4 $end
$var wire 1 # clk $end
$var wire 1 C reset $end
$var wire 1 D sw $end
$var wire 19 E q_next [18:0] $end
$var wire 1 F m_tick $end
$var reg 1 G db $end
$var reg 19 H q_reg [18:0] $end
$var reg 3 I state_next [2:0] $end
$var reg 3 J state_reg [2:0] $end
$upscope $end
$scope module eboton1 $end
$var wire 1 # clk $end
$var wire 1 K level $end
$var wire 1 L reset $end
$var wire 1 M tick $end
$var reg 1 N delay_reg $end
$upscope $end
$scope module eboton2 $end
$var wire 1 # clk $end
$var wire 1 O level $end
$var wire 1 P reset $end
$var wire 1 Q tick $end
$var reg 1 R delay_reg $end
$upscope $end
$scope module eboton3 $end
$var wire 1 # clk $end
$var wire 1 S level $end
$var wire 1 T reset $end
$var wire 1 U tick $end
$var reg 1 V delay_reg $end
$upscope $end
$scope module eboton4 $end
$var wire 1 # clk $end
$var wire 1 W level $end
$var wire 1 X reset $end
$var wire 1 Y tick $end
$var reg 1 Z delay_reg $end
$upscope $end
$scope module inversador $end
$var wire 4 [ in [3:0] $end
$var wire 4 \ out [3:0] $end
$upscope $end
$upscope $end
$upscope $end
$enddefinitions $end
#0
$dumpvars
bx \
bx [
xZ
0Y
0X
0W
xV
0U
0T
0S
xR
0Q
0P
0O
xN
0M
0L
0K
bx J
b0 I
bx H
0G
xF
bx E
xD
0C
bx B
b0 A
bx @
0?
x>
bx =
x<
0;
bx :
b0 9
bx 8
07
x6
bx 5
x4
03
bx 2
b0 1
bx 0
0/
x.
bx -
x,
0+
b0 *
bx )
b0 (
b0 '
b0 &
bx %
1$
0#
bx "
b0 !
$end
#50000
b0 2
b0 :
b0 B
b0 J
0N
0R
0V
0Z
1#
#100000
b1 I
b1 A
b1 9
b1 1
1D
1<
14
1,
b1111 )
b1111 \
0#
b0 "
b0 %
b0 [
#150000
b1 2
b1 :
b1 B
b1 J
1#
#200000
0#
#250000
1#
#300000
0#
#350000
1#
#400000
0#
#450000
1#
#500000
0#
#550000
1#
#600000
0#
#650000
1#
#700000
0#
#750000
1#
#800000
0#
#850000
1#
#900000
0#
#950000
1#
#1000000
0#
#1050000
1#
#1100000
0#
#1150000
1#
#1200000
0#
#1250000
1#
#1300000
0#
#1350000
1#
#1400000
0#
#1450000
1#
#1500000
0#
#1550000
1#
#1600000
0#
#1650000
1#
#1700000
0#
#1750000
1#
#1800000
0#
#1850000
1#
#1900000
0#
#1950000
1#
#2000000
0#
#2050000
1#
#2100000
0#
#2150000
1#
#2200000
0#
#2250000
1#
#2300000
0#
#2350000
1#
#2400000
0#
#2450000
1#
#2500000
0#
#2550000
1#
#2600000
0#
#2650000
1#
#2700000
0#
#2750000
1#
#2800000
0#
#2850000
1#
#2900000
0#
#2950000
1#
#3000000
0#
#3050000
1#
#3100000
0#
#3150000
1#
#3200000
0#
#3250000
1#
#3300000
0#
#3350000
1#
#3400000
0#
#3450000
1#
#3500000
0#
#3550000
1#
#3600000
0#
#3650000
1#
#3700000
0#
#3750000
1#
#3800000
0#
#3850000
1#
#3900000
0#
#3950000
1#
#4000000
0#
#4050000
1#
#4100000
0#
#4150000
1#
#4200000
0#
#4250000
1#
#4300000
0#
#4350000
1#
#4400000
0#
#4450000
1#
#4500000
0#
#4550000
1#
#4600000
0#
#4650000
1#
#4700000
0#
#4750000
1#
#4800000
0#
#4850000
1#
#4900000
0#
#4950000
1#
#5000000
0#
#5050000
1#
#5100000
0#
#5150000
1#
#5200000
0#
#5250000
1#
#5300000
0#
#5350000
1#
#5400000
0#
#5450000
1#
#5500000
0#
#5550000
1#
#5600000
0#
#5650000
1#
#5700000
0#
#5750000
1#
#5800000
0#
#5850000
1#
#5900000
0#
#5950000
1#
#6000000
0#
#6050000
1#
#6100000
0#
#6150000
1#
#6200000
0#
#6250000
1#
#6300000
0#
#6350000
1#
#6400000
0#
#6450000
1#
#6500000
0#
#6550000
1#
#6600000
0#
#6650000
1#
#6700000
0#
#6750000
1#
#6800000
0#
#6850000
1#
#6900000
0#
#6950000
1#
#7000000
0#
#7050000
1#
#7100000
b0 1
0,
b1110 )
b1110 \
0#
b1 "
b1 %
b1 [
#7150000
b0 2
1#
#7200000
0#
#7250000
1#
#7300000
0#
#7350000
1#
#7400000
0#
#7450000
1#
#7500000
0#
#7550000
1#
#7600000
0#
#7650000
1#
#7700000
0#
#7750000
1#
#7800000
0#
#7850000
1#
#7900000
0#
#7950000
1#
#8000000
0#
#8050000
1#
#8100000
0#
#8150000
1#
#8200000
0#
#8250000
1#
#8300000
0#
#8350000
1#
#8400000
0#
#8450000
1#
#8500000
0#
#8550000
1#
#8600000
0#
#8650000
1#
#8700000
0#
#8750000
1#
#8800000
0#
#8850000
1#
#8900000
0#
#8950000
1#
#9000000
0#
#9050000
1#
#9100000
0#
#9150000
1#
#9200000
0#
#9250000
1#
#9300000
0#
#9350000
1#
#9400000
0#
#9450000
1#
#9500000
0#
#9550000
1#
#9600000
0#
#9650000
1#
#9700000
0#
#9750000
1#
#9800000
0#
#9850000
1#
#9900000
0#
#9950000
1#
#10000000
0#
#10050000
1#
#10100000
b1 1
1,
b1111 )
b1111 \
0#
b0 "
b0 %
b0 [
#10150000
b1 2
1#
