deboundcer/db_fsm.v
module db_fsm(
    input wire clk, 
    input wire reset,
    input wire sw,
    output reg db
);
//symbolic state declaration
localparam [2:0]
            zero = 3'b000,
            wait1_1 = 3'b001,
            wait1_2 = 3'b010,
            wait1_3 = 3'b011,
            one = 3'b100,
            wait0_1 = 3'b101,
            wait0_2 = 3'b110,
            wait0_3 = 3'b111;

//number of counter bits(2^N*20ns = 10ms tick)
localparam N=19;

//signal declaration
reg[N-1:0] q_reg;
wire [N-1:0] q_next;
wire m_tick;
reg [2:0] state_reg, state_next;

//body
//counter to generate 10ms tick

always @(posedge clk)
    begin
    q_reg <= q_next;
    end
//next-state logic
assign q_next = q_reg+1;
//output tick
assign m_tick = (q_reg == 0) ? 1'b1 : 1'b0;

//debouncing FSM
//state register
always @(posedge clk, posedge(reset))
    if(reset)
        state_reg <= zero;
    else
        state_reg <= state_next;

//next-state logic and output logic
always @*
begin
    state_next = state_reg; //default state : the same
    db = 1'b0;              //default output:0
    case(state_reg)
        zero:
            if(sw)
                state_next = wait1_1;
        wait1_1:
            if(~sw)
                state_next = zero;
            else
                if(m_tick)
                    state_next = wait1_2;
        wait1_2:
            if(~sw)
                state_next = zero;
            else
                if (m_tick)
                    state_next = wait1_3;
        wait1_3:
            if (~sw)
                state_next = zero;
            else
                if(m_tick)
                    state_next = one;
        one:
            begin
                db = 1'b1;
                if(~sw)
                    state_next = wait0_1;
            end
        wait0_1:
            begin
                db = 1'b1;
                if(sw)
                    state_next = one;
                else
                    if(m_tick)
                        state_next = wait0_2;
            end
        wait0_2:
            begin
                db = 1'b1;
                if (sw)
                    state_next = one;
                else
                    if (m_tick)
                        state_next = wait0_3;
            end
        wait0_3:
            begin
                db = 1'b1;
                if(sw)
                    state_next = one;
                else
                    if(m_tick)
                        state_next = zero;
            end
        default: state_next = zero;
    endcase
end
endmodule

deboundcer/dbsNoFuncan/db_fsm_tb.v
`default_nettype none
`define DUMPSTR(x) `"x.vcd`"
`timescale 100 ns / 10 ns
module db_fsm_tb;
parameter DURATION = 50;


reg clk = 0;
always #0.5 clk = ~clk;
reg reset;
reg senial;
wire salidita;


db_fsm UUT (
    .clk(clk),
    .reset(reset),
    .sw(senial),
    .db(salidita)
);



initial begin
  $dumpfile(`DUMPSTR(`VCD_OUTPUT));
  $dumpvars(0, db_fsm_tb);
    reset= 1;
    #1
    senial = 0;
    reset = 0;
    #7
    senial = 1;

    #3
    senial = 0;

    #4
    senial = 1;

    #2
    senial = 0;
    #2
    senial = 1;

    #3
    senial = 0;
    
    #5
    senial = 1;

    //Numerador
   
   #(DURATION) $display("End of simulation");
  $finish;
end

endmodule

deboundcer/dbsNoFuncan/db_fsm_tb.vcd
$date
	Wed Jun 21 15:54:52 2023
$end
$version
	Icarus Verilog
$end
$timescale
	1ps
$end
$scope module db_fsm_tb $end
$var wire 1 ! salidita $end
$var reg 1 " clk $end
$var reg 1 # reset $end
$var reg 1 $ senial $end
$scope module UUT $end
$var wire 1 " clk $end
$var wire 1 # reset $end
$var wire 1 $ sw $end
$var wire 19 % q_next [18:0] $end
$var wire 1 & m_tick $end
$var reg 1 ! db $end
$var reg 19 ' q_reg [18:0] $end
$var reg 3 ( state_next [2:0] $end
$var reg 3 ) state_reg [2:0] $end
$upscope $end
$upscope $end
$enddefinitions $end
#0
$dumpvars
b0 )
b0 (
bx '
x&
bx %
x$
1#
0"
0!
$end
#50000
1"
#100000
0"
0#
0$
#150000
1"
#200000
0"
#250000
1"
#300000
0"
#350000
1"
#400000
0"
#450000
1"
#500000
0"
#550000
1"
#600000
0"
#650000
1"
#700000
0"
#750000
1"
#800000
b1 (
0"
1$
#850000
b1 )
1"
#900000
0"
#950000
1"
#1000000
0"
#1050000
1"
#1100000
b0 (
0"
0$
#1150000
b0 )
1"
#1200000
0"
#1250000
1"
#1300000
0"
#1350000
1"
#1400000
0"
#1450000
1"
#1500000
b1 (
0"
1$
#1550000
b1 )
1"
#1600000
0"
#1650000
1"
#1700000
b0 (
0"
0$
#1750000
b0 )
1"
#1800000
0"
#1850000
1"
#1900000
b1 (
0"
1$
#1950000
b1 )
1"
#2000000
0"
#2050000
1"
#2100000
0"
#2150000
1"
#2200000
b0 (
0"
0$
#2250000
b0 )
1"
#2300000
0"
#2350000
1"
#2400000
0"
#2450000
1"
#2500000
0"
#2550000
1"
#2600000
0"
#2650000
1"
#2700000
b1 (
0"
1$
#2750000
b1 )
1"
